{"horaCorte":"00:37","fechaCorte":"02 de julio de 2018","cortePrueba":false,"corteEspeciales":false,"archivoCorte":"20180702_0037_PREP.zip","nivelNodo":"NACIONAL","idNodo":100,"nombreNodo":"","totalActas":156840,"totalActasMR":156808,"totalActasUrbanas":18378,"totalActasRurales":4945,"actasContabilizadas":{"total":23323,"porcentaje":14.8705},"actasContabilizadasMR":{"total":23323,"porcentaje":14.8705},"actasCapturadas":{"total":23403,"porcentaje":14.9215},"listaNominalOficial":89250881,"participacionActasContabilizadas":14.5407,"listaNominal":12977770,"porcentajeParticipacionCiudadana":62.8374,"porcentajeTotalVotos":100.0000,"totalVotos":8238983,"totalVotosVN":8238983,"totalVotosVE":0,"totalVotosBasicasMR":8154905,"totalVotosEspecialesMR":84078,"idPartidoCoalicionMayoriaVotos":30,"votacionPartidosConDistribucion":[{"idPartido":1,"nombrePartido":"PARTIDO ACCIÓN NACIONAL","siglasPartido":"PAN","emblemaPartido":"pan.png","colorPartido":"0045AD","total":1727485,"porcentaje":20.9672,"totalVN":1727485,"totalVE":0},{"idPartido":2,"nombrePartido":"PARTIDO REVOLUCIONARIO INSTITUCIONAL","siglasPartido":"PRI","emblemaPartido":"pri.png","colorPartido":"009640","total":1056409,"porcentaje":12.8220,"totalVN":1056409,"totalVE":0},{"idPartido":3,"nombrePartido":"PARTIDO DE LA REVOLUCIÓN DEMOCRÁTICA","siglasPartido":"PRD","emblemaPartido":"prd.png","colorPartido":"EAC52F","total":203971,"porcentaje":2.4756,"totalVN":203971,"totalVE":0},{"idPartido":4,"nombrePartido":"PARTIDO VERDE ECOLOGISTA DE MÉXICO","siglasPartido":"PVEM","emblemaPartido":"pvem.png","colorPartido":"A0CE67","total":103260,"porcentaje":1.2533,"totalVN":103260,"totalVE":0},{"idPartido":5,"nombrePartido":"PARTIDO DEL TRABAJO","siglasPartido":"PT","emblemaPartido":"pt.png","colorPartido":"EB0028","total":435890,"porcentaje":5.2905,"totalVN":435890,"totalVE":0},{"idPartido":6,"nombrePartido":"MOVIMIENTO CIUDADANO","siglasPartido":"MOVIMIENTO CIUDADANO","emblemaPartido":"mc.png","colorPartido":"FF8200","total":145033,"porcentaje":1.7603,"totalVN":145033,"totalVE":0},{"idPartido":7,"nombrePartido":"NUEVA ALIANZA","siglasPartido":"NUEVA ALIANZA","emblemaPartido":"na.png","colorPartido":"14B4B6","total":66589,"porcentaje":0.8082,"totalVN":66589,"totalVE":0},{"idPartido":8,"nombrePartido":"MOVIMIENTO REGENERACIÓN NACIONAL","siglasPartido":"MORENA","emblemaPartido":"morena.png","colorPartido":"C0311A","total":3577506,"porcentaje":43.4216,"totalVN":3577506,"totalVE":0},{"idPartido":9,"nombrePartido":"ENCUENTRO SOCIAL","siglasPartido":"ENCUENTRO SOCIAL ","emblemaPartido":"es.png","colorPartido":"662781","total":204695,"porcentaje":2.4844,"totalVN":204695,"totalVE":0},{"idPartido":51,"nombrePartido":"CANDIDATO INDEPENDIENTE 1","siglasPartido":"CI_01","emblemaPartido":"ci_0151.png","colorPartido":"8AA89D","total":10796,"porcentaje":0.1310,"totalVN":10796,"totalVE":0},{"idPartido":52,"nombrePartido":"CANDIDATO INDEPENDIENTE 2","siglasPartido":"CI_02","emblemaPartido":"ci_0252.png","colorPartido":"CA9E67","total":508068,"porcentaje":6.1666,"totalVN":508068,"totalVE":0},{"idPartido":61,"nombrePartido":"CANDIDATURAS NO REGISTRADAS","siglasPartido":"CNR","emblemaPartido":"noregistrados.png","colorPartido":"D8BC8F","total":9078,"porcentaje":0.1101,"totalVN":9078,"totalVE":0},{"idPartido":62,"nombrePartido":"VOTOS NULOS","siglasPartido":"VN","emblemaPartido":"nulos.png","colorPartido":"D1D1D1","total":190203,"porcentaje":2.3085,"totalVN":190203,"totalVE":0}],"votosCandidatoPartidoCoalicion":[{"idPartido":20,"nombrePartido":"COALICIÓN POR MÉXICO AL FRENTE (PAN-PRD-MC)","siglasPartido":"PAN-PRD-MC","emblemaPartido":"pan_prd_mc.png","colorPartido":"669FF1","idCandidatoPropietario":1,"idCandidatoSuplente":0,"nombreCandidatoPropietario":"Ricardo Anaya Cortés","fotoCandidatoPropietario":"FOTO_1.jpg","nombreCandidatoSuplente":"","idSubcoaliciones":[21,22,23,1,3,6],"idsSubMosaico":[1,3,6],"total":2076489,"porcentaje":25.2032,"totalVN":2076489,"totalVE":0},{"idPartido":40,"nombrePartido":"TODOS POR MÉXICO (PRI-PVEM-NA)","siglasPartido":"PRI-PVEM-NA","emblemaPartido":"pri_pvem_panal.png","colorPartido":"82E0A8","idCandidatoPropietario":2,"idCandidatoSuplente":0,"nombreCandidatoPropietario":"José Antonio Meade Kuribreña","fotoCandidatoPropietario":"FOTO_2.jpg","nombreCandidatoSuplente":"","idSubcoaliciones":[41,42,43,2,4,7],"idsSubMosaico":[2,4,7],"total":1226258,"porcentaje":14.8836,"totalVN":1226258,"totalVE":0},{"idPartido":30,"nombrePartido":"JUNTOS HAREMOS HISTORIA (PT-MORENA-ES)","siglasPartido":"PT-MORENA-PES","emblemaPartido":"pt_morena_es.png","colorPartido":"F28F8F","idCandidatoPropietario":5,"idCandidatoSuplente":0,"nombreCandidatoPropietario":"Andrés Manuel López Obrador","fotoCandidatoPropietario":"FOTO_5.jpg","nombreCandidatoSuplente":"","idSubcoaliciones":[31,32,33,5,8,9],"idsSubMosaico":[5,8,9],"total":4218091,"porcentaje":51.1967,"totalVN":4218091,"totalVE":0},{"idPartido":51,"nombrePartido":"CANDIDATO INDEPENDIENTE 1","siglasPartido":"CI_01","emblemaPartido":"ci_0151.png","colorPartido":"8AA89D","idCandidatoPropietario":51,"idCandidatoSuplente":0,"nombreCandidatoPropietario":"Margarita Ester Zavala Gómez del Campo","fotoCandidatoPropietario":"FOTO_51.jpg","nombreCandidatoSuplente":"","idSubcoaliciones":[],"idsSubMosaico":[],"total":10796,"porcentaje":0.1310,"totalVN":10796,"totalVE":0},{"idPartido":52,"nombrePartido":"CANDIDATO INDEPENDIENTE 2","siglasPartido":"CI_02","emblemaPartido":"ci_0252.png","colorPartido":"CA9E67","idCandidatoPropietario":52,"idCandidatoSuplente":0,"nombreCandidatoPropietario":"Jaime Heliodoro Rodríguez Calderón","fotoCandidatoPropietario":"FOTO_52.jpg","nombreCandidatoSuplente":"","idSubcoaliciones":[],"idsSubMosaico":[],"total":508068,"porcentaje":6.1666,"totalVN":508068,"totalVE":0},{"idPartido":61,"nombrePartido":"CANDIDATURAS NO REGISTRADAS","siglasPartido":"CNR","emblemaPartido":"noregistrados.png","colorPartido":"D8BC8F","idCandidatoPropietario":61,"idCandidatoSuplente":0,"nombreCandidatoPropietario":"","fotoCandidatoPropietario":"","nombreCandidatoSuplente":"","idSubcoaliciones":[],"idsSubMosaico":[],"total":9078,"porcentaje":0.1101,"totalVN":9078,"totalVE":0},{"idPartido":62,"nombrePartido":"VOTOS NULOS","siglasPartido":"VN","emblemaPartido":"nulos.png","colorPartido":"D1D1D1","idCandidatoPropietario":62,"idCandidatoSuplente":0,"nombreCandidatoPropietario":"","fotoCandidatoPropietario":"","nombreCandidatoSuplente":"","idSubcoaliciones":[],"idsSubMosaico":[],"total":190203,"porcentaje":2.3085,"totalVN":190203,"totalVE":0}],"entidadesContadas":{"total":32,"porcentaje":100.0},"numeroEntidades":32}